test/__init__.py
test/config/__init__.py
test/config/test_config_yml.py
test/file/__init__.py
test/file/test_file.py
test/handler/__init__.py
test/helper/__init__.py
test/helper/test_data_helper.py
test/helper/test_string_helper.py
test/helper/test_url_helper.py
und_microservice/__init__.py
und_microservice/adapter/__init__.py
und_microservice/adapter/sqlalchemy.py
und_microservice/adapter/exception/__init__.py
und_microservice/api/__init__.py
und_microservice/api/falcon_api.py
und_microservice/commons/__init__.py
und_microservice/commons/file.py
und_microservice/config/__init__.py
und_microservice/config/base.py
und_microservice/config/config_yaml.py
und_microservice/config/exception/__init__.py
und_microservice/config/exception/config.py
und_microservice/handler/__init__.py
und_microservice/handler/base.py
und_microservice/handler/decorator/__init__.py
und_microservice/handler/decorator/service.py
und_microservice/handler/exception/__init__.py
und_microservice/handler/middlewares/__init__.py
und_microservice/handler/middlewares/basic.py
und_microservice/helper/__init__.py
und_microservice/helper/data.py
und_microservice/helper/env.py
und_microservice/helper/string.py
und_microservice/helper/try_except.py
und_microservice/helper/url.py
und_microservice/logger/__init__.py
und_microservice/logger/logging.py
und_microservice/response/__init__.py
und_microservice/response/orbis.py
und_microservice-0.0.16.dist-info/METADATA
und_microservice-0.0.16.dist-info/RECORD
und_microservice-0.0.16.dist-info/WHEEL
und_microservice-0.0.16.dist-info/top_level.txt
