Metadata-Version: 2.1
Name: und-microservice
Version: 0.0.16
Summary: UND microservices common utilities
Home-page: https://github.com/und-tech/und-python-microservice
Author: UND
Author-email: development@orbis.com.pe
License: UNKNOWN
Platform: UNKNOWN
Classifier: Programming Language :: Python :: 3
Classifier: License :: OSI Approved :: MIT License
Classifier: Operating System :: OS Independent
Requires-Dist: falcon (==1.4.1)
Requires-Dist: PyYAML (==3.12)
Requires-Dist: PyMySQL (==0.8.0)
Requires-Dist: SQLAlchemy (==1.2.2)
Requires-Dist: requests (==2.18.4)
Requires-Dist: click (==6.0)
Requires-Dist: falcon-auth (==1.1.0)
Requires-Dist: querystring-parser (==1.2.3)
Requires-Dist: python-dotenv (==0.9.1)
Requires-Dist: nose (==1.3.7)
Requires-Dist: coverage (==4.5.1)
Requires-Dist: psycopg2 (==2.7.5)
Requires-Dist: pytest
